bs_monitor/__init__.py
bs_monitor/job_runner.py
bs_monitor/monitor_cli.py
bs_monitor/monitor_manager.py
bs_monitor/monitor_server_impl.py
bs_monitor/monitor_server_impl_async.py
bs_monitor/monitor_util.py
bs_monitor/braze/__init__.py
bs_monitor/braze/bbatch_inst_query.py
bs_monitor/braze/bbatch_query.py
bs_monitor/braze/bjob_inst_query.py
bs_monitor/braze/blazy_load.py
bs_monitor/braze/monitor_async_server_interface.py
bs_monitor/braze/monitor_async_server_marshaler.py
bs_monitor/braze/monitor_client_interface.py
bs_monitor/braze/monitor_client_marshaler.py
bs_monitor/braze/monitor_client_server_impl.py
bs_monitor/braze/monitor_server_interface.py
bs_monitor/braze/monitor_server_marshaler.py
bs_monitor/db/__init__.py
bs_monitor/db/dao/postgresql/__init__.py
bs_monitor/db/dao/postgresql/batch.py
bs_monitor/db/dao/postgresql/batch_by_name.py
bs_monitor/db/dao/postgresql/batch_by_parent.py
bs_monitor/db/dao/postgresql/batch_delete_one.py
bs_monitor/db/dao/postgresql/batch_for_scheduling.py
bs_monitor/db/dao/postgresql/batch_insert.py
bs_monitor/db/dao/postgresql/batch_inst.py
bs_monitor/db/dao/postgresql/batch_inst_all_children_completed.py
bs_monitor/db/dao/postgresql/batch_inst_delete_one.py
bs_monitor/db/dao/postgresql/batch_inst_for_processing.py
bs_monitor/db/dao/postgresql/batch_inst_insert.py
bs_monitor/db/dao/postgresql/batch_inst_lock_one.py
bs_monitor/db/dao/postgresql/batch_inst_not_completed.py
bs_monitor/db/dao/postgresql/batch_inst_purge.py
bs_monitor/db/dao/postgresql/batch_inst_search.py
bs_monitor/db/dao/postgresql/batch_inst_select_one.py
bs_monitor/db/dao/postgresql/batch_inst_update.py
bs_monitor/db/dao/postgresql/batch_item.py
bs_monitor/db/dao/postgresql/batch_item_by_batch_id.py
bs_monitor/db/dao/postgresql/batch_item_delete_by_batch_id.py
bs_monitor/db/dao/postgresql/batch_item_delete_one.py
bs_monitor/db/dao/postgresql/batch_item_for_inserting.py
bs_monitor/db/dao/postgresql/batch_item_insert.py
bitsmiths_monitor-2.2.2.dist-info/LICENCE
bitsmiths_monitor-2.2.2.dist-info/METADATA
bitsmiths_monitor-2.2.2.dist-info/WHEEL
bitsmiths_monitor-2.2.2.dist-info/entry_points.txt
bitsmiths_monitor-2.2.2.dist-info/top_level.txt
bitsmiths_monitor-2.2.2.dist-info/RECORD
